{
  "template": {
    "version": "vYYYY.MM.DD or semantic version",
    "date": "ISO-8601 release date",
    "changes": [
      {
        "type": "added | changed | fixed | removed",
        "area": "subsystem or feature name",
        "description": "Concise summary of the change",
        "commit": "git hash or link",
        "files_affected": [
          "List of key files or directories impacted"
        ],
        "issues": [
          "Optional list of bug IDs or tickets"
        ]
      }
    ]
  },
  "entries": [
    {
      "version": "v0.5.0",
      "date": "2026-01-15",
      "changes": [
        {
          "type": "added",
          "area": "tools.executor",
          "description": "ToolExecutor now exposes spawn_subpipeline(), enabling tools to launch child pipelines via SubpipelineSpawner with a single call.",
          "commit": "pending",
          "files_affected": [
            "stageflow/tools/executor.py",
            "docs/advanced/subpipelines.md"
          ],
          "issues": []
        },
        {
          "type": "changed",
          "area": "observability",
          "description": "Spawn operations emit structured ToolExecutor logs and surface SubpipelineResult metadata for improved tracing.",
          "commit": "pending",
          "files_affected": [
            "stageflow/tools/executor.py",
            "docs/index.md"
          ],
          "issues": []
        },
        {
          "type": "added",
          "area": "testing",
          "description": "Introduced dedicated unit/integration suites covering subpipeline spawning, depth limits, registry lookup errors, and event emission.",
          "commit": "pending",
          "files_affected": [
            "tests/unit/tools/test_spawn_subpipeline.py",
            "tests/integration/test_subpipelines.py"
          ],
          "issues": []
        }
      ]
    },
    {
      "version": "v0.4.0",
      "date": "2026-01-15",
      "changes": [
        {
          "type": "added",
          "area": "websearch.run_utils",
          "description": "Introduced high-level helpers (fetch_page/fetch_pages/fetch_with_retry/search_and_extract/map_site/extract_all_links) plus FetchProgress, SearchResult, and SiteMap dataclasses for accelerated agent workflows.",
          "commit": "bfc01a25aabf9f3b566c2164b5ca8c71d5340a95",
          "files_affected": [
            "stageflow/websearch/run_utils.py",
            "stageflow/websearch/__init__.py",
            "tests/websearch/test_run_utils.py",
            "docs/guides/websearch.md"
          ],
          "issues": []
        },
        {
          "type": "fixed",
          "area": "websearch.navigation",
          "description": "FallbackNavigator now inspects each anchor tag individually, preventing pagination loops and improving multi-page crawling stability.",
          "commit": "bfc01a25aabf9f3b566c2164b5ca8c71d5340a95",
          "files_affected": [
            "stageflow/websearch/navigator.py",
            "tests/websearch/test_client.py"
          ],
          "issues": []
        },
        {
          "type": "added",
          "area": "performance",
          "description": "fetch_pages gained optional parallel extraction backed by a shared ThreadPoolExecutor to overlap CPU-bound HTML parsing with HTTP I/O.",
          "commit": "pending",
          "files_affected": [
            "stageflow/websearch/run_utils.py"
          ],
          "issues": []
        },
        {
          "type": "added",
          "area": "docs",
          "description": "Documented selectolax recommendation, client lifecycle guidance, run utilities, and new release highlights across README and docs/index.",
          "commit": "pending",
          "files_affected": [
            "docs/guides/websearch.md",
            "docs/index.md",
            "README.md"
          ],
          "issues": []
        }
      ]
    },
    {
      "version": "v0.3.0",
      "date": "2026-01-14",
      "changes": [
        {
          "type": "fixed",
          "area": "stages.inputs",
          "description": "StageInputs now validates keys to prevent None/empty lookups from silently dropping upstream data.",
          "commit": "bfc01a25aabf9f3b566c2164b5ca8c71d5340a95",
          "issues": [
            "BUG-20260114-01"
          ]
        },
        {
          "type": "added",
          "area": "docs",
          "description": "Added StageInputs API reference, updated stage guide, and linked docs to reflect validation rules.",
          "commit": "bfc01a25aabf9f3b566c2164b5ca8c71d5340a95",
          "issues": []
        },
        {
          "type": "added",
          "area": "ci",
          "description": "Introduced GitHub Actions workflow to run pytest across unit, integration, property, execution, framework, contract, configuration, and utils suites.",
          "commit": "pending",
          "issues": []
        },
        {
          "type": "added",
          "area": "websearch",
          "description": "Added web search module with async HTTP fetching, HTML-to-markdown extraction preserving structure, and page navigation capabilities.",
          "commit": "ace7cb0",
          "files_affected": [
            "stageflow/websearch/*",
            "docs/guides/websearch.md",
            "tests/websearch/*",
            "pyproject.toml",
            "changelog.json"
          ],
          "issues": []
        }
      ]
    }
  ]
}
